{"schemaVersion":"1.0.0","readme":"","modules":[{"kind":"javascript-module","path":"src/text-field.ts","declarations":[{"kind":"class","description":"","name":"TextField","cssProperties":[{"type":{"text":"border-radius"},"name":"--c2-text-field--border-top-left-radius","default":"4px"},{"type":{"text":"border-radius"},"name":"--c2-text-field--border-top-right-radius","default":"4px"},{"type":{"text":"border-radius"},"name":"--c2-text-field--border-bottom-left-radius","default":"4px"},{"type":{"text":"border-radius"},"name":"--c2-text-field--border-bottom-right-radius","default":"4px"},{"type":{"text":"padding"},"name":"--c2-text-field--padding-top","default":"8px"},{"type":{"text":"padding"},"name":"--c2-text-field--padding-right","default":"8px"},{"type":{"text":"padding"},"name":"--c2-text-field--padding-bottom","default":"8px"},{"type":{"text":"padding"},"name":"--c2-text-field--padding-left","default":"8px"},{"type":{"text":"border"},"name":"--c2-text-field--border-top","default":"1px solid rgb(177, 177, 177)"},{"type":{"text":"border"},"name":"--c2-text-field--border-right","default":"1px solid rgb(177, 177, 177)"},{"type":{"text":"border"},"name":"--c2-text-field--border-bottom","default":"1px solid rgb(177, 177, 177)"},{"type":{"text":"border"},"name":"--c2-text-field--border-left","default":"1px solid rgb(177, 177, 177)"},{"type":{"text":"color"},"name":"--c2-text-field--color"},{"type":{"text":"background"},"name":"--c2-text-field--background","default":"field"},{"type":{"text":"font-size"},"name":"--c2-text-field--font-size"},{"type":{"text":"font-weight"},"name":"--c2-text-field--font-weight"},{"type":{"text":"font-style"},"name":"--c2-text-field--font-style"},{"type":{"text":"font-family"},"name":"--c2-text-field--font-family"},{"type":{"text":"opacity"},"name":"--c2-text-field__placeholder--opacity","default":"0.5"},{"type":{"text":"font-weight"},"name":"--c2-text-field__placeholder--font-weight"},{"type":{"text":"font-style"},"name":"--c2-text-field__placeholder--font-style"},{"type":{"text":"color"},"name":"--c2-text-field__placeholder--color"},{"type":{"text":"border"},"name":"--c2-text-field__focus--border-top","default":"1px solid rgb(2, 101, 220)"},{"type":{"text":"border"},"name":"--c2-text-field__focus--border-right","default":"1px solid rgb(2, 101, 220)"},{"type":{"text":"border"},"name":"--c2-text-field__focus--border-bottom","default":"1px solid rgb(2, 101, 220)"},{"type":{"text":"border"},"name":"--c2-text-field__focus--border-left","default":"1px solid rgb(2, 101, 220)"},{"type":{"text":"color"},"name":"--c2-text-field__focus--color"},{"type":{"text":"background"},"name":"--c2-text-field__focus--background"},{"type":{"text":"border"},"name":"--c2-text-field__error--border-top","default":"1px solid rgb(211, 21, 16)"},{"type":{"text":"border"},"name":"--c2-text-field__error--border-right","default":"1px solid rgb(211, 21, 16)"},{"type":{"text":"border"},"name":"--c2-text-field__error--border-bottom","default":"1px solid rgb(211, 21, 16)"},{"type":{"text":"border"},"name":"--c2-text-field__error--border-left","default":"1px solid rgb(211, 21, 16)"},{"type":{"text":"color"},"name":"--c2-text-field__error--color","default":"rgb(211, 21, 16)"},{"type":{"text":"background"},"name":"--c2-text-field__error--background"},{"type":{"text":"border"},"name":"--c2-text-field__read-only--border-top","default":"unset"},{"type":{"text":"border"},"name":"--c2-text-field__read-only--border-right","default":"unset"},{"type":{"text":"border"},"name":"--c2-text-field__read-only--border-bottom","default":"unset"},{"type":{"text":"border"},"name":"--c2-text-field__read-only--border-left","default":"unset"},{"type":{"text":"color"},"name":"--c2-text-field__read-only--color"},{"type":{"text":"background"},"name":"--c2-text-field__read-only--background","default":"transparent"}],"members":[{"kind":"field","name":"readOnly","type":{"text":"boolean"},"default":"false","attribute":"readOnly","reflects":true},{"kind":"field","name":"disabled","type":{"text":"boolean"},"default":"false","attribute":"disabled","reflects":true},{"kind":"field","name":"error","type":{"text":"boolean"},"default":"false","attribute":"error","reflects":true},{"kind":"field","name":"maxLength","type":{"text":"number"},"default":"-1","attribute":"maxLength"},{"kind":"field","name":"minLength","type":{"text":"number"},"default":"-1","attribute":"minLength"},{"kind":"field","name":"pattern","type":{"text":"string"},"default":"''","attribute":"pattern"},{"kind":"field","name":"required","type":{"text":"boolean"},"default":"false","attribute":"required","reflects":true},{"kind":"field","name":"placeholder","type":{"text":"string"},"default":"''","attribute":"placeholder"},{"kind":"field","name":"value","type":{"text":"string"},"default":"''","attribute":"value"},{"kind":"field","name":"errorText","type":{"text":"string"},"default":"''","attribute":"error-text"},{"kind":"field","name":"help","type":{"text":"string"},"default":"''","attribute":"help"},{"kind":"field","name":"dirty","type":{"text":"boolean"},"privacy":"private","default":"false"},{"kind":"field","name":"focused","type":{"text":"boolean"},"privacy":"private","default":"false"},{"kind":"field","name":"input","type":{"text":"HTMLInputElement | null | undefined"},"privacy":"private","readonly":true},{"kind":"method","name":"reset"},{"kind":"field","name":"handleFocus"},{"kind":"method","name":"isDirty"},{"kind":"method","name":"focus","return":{"type":{"text":"void"}},"parameters":[{"name":"options","optional":true,"type":{"text":"FocusOptions | undefined"}}]},{"kind":"method","name":"handleInput","privacy":"protected","parameters":[{"name":"event","type":{"text":"InputEvent"}}]},{"kind":"method","name":"handleFocusin","privacy":"protected","parameters":[{"name":"event","type":{"text":"Event"}}]},{"kind":"method","name":"forwardFocusin","privacy":"protected","parameters":[{"name":"event","type":{"text":"Event"}}]},{"kind":"method","name":"handleFocusout","privacy":"protected","parameters":[{"name":"event","type":{"text":"Event"}}]},{"kind":"method","name":"renderPrefixSlot","privacy":"protected"},{"kind":"method","name":"renderSuffixSlot","privacy":"protected"},{"kind":"method","name":"renderHelpIconSlot","privacy":"protected"},{"kind":"method","name":"renderSupportingTextSlot","privacy":"protected"},{"kind":"method","name":"redispatchEvent","privacy":"private","parameters":[{"name":"event","type":{"text":"Event"}}]}],"attributes":[{"name":"readOnly","type":{"text":"boolean"},"default":"false","fieldName":"readOnly"},{"name":"disabled","type":{"text":"boolean"},"default":"false","fieldName":"disabled"},{"name":"error","type":{"text":"boolean"},"default":"false","fieldName":"error"},{"name":"maxLength","type":{"text":"number"},"default":"-1","fieldName":"maxLength"},{"name":"minLength","type":{"text":"number"},"default":"-1","fieldName":"minLength"},{"name":"pattern","type":{"text":"string"},"default":"''","fieldName":"pattern"},{"name":"required","type":{"text":"boolean"},"default":"false","fieldName":"required"},{"name":"placeholder","type":{"text":"string"},"default":"''","fieldName":"placeholder"},{"name":"value","type":{"text":"string"},"default":"''","fieldName":"value"},{"name":"error-text","type":{"text":"string"},"default":"''","fieldName":"errorText"},{"name":"help","type":{"text":"string"},"default":"''","fieldName":"help"}],"superclass":{"name":"LitElement","package":"lit"},"tagName":"c2-text-field","customElement":true}],"exports":[{"kind":"js","name":"TextField","declaration":{"name":"TextField","module":"src/text-field.ts"}},{"kind":"custom-element-definition","name":"c2-text-field","declaration":{"name":"TextField","module":"src/text-field.ts"}}]}]}